casbin_pymongo_adapter/__init__.py
casbin_pymongo_adapter/_filter.py
casbin_pymongo_adapter/_rule.py
casbin_pymongo_adapter/adapter.py
casbin_pymongo_adapter/asynchronous/__init__.py
casbin_pymongo_adapter/asynchronous/adapter.py
casbin_pymongo_adapter-1.6.0.data/data/README.md
casbin_pymongo_adapter-1.6.0.dist-info/licenses/LICENSE
casbin_pymongo_adapter-1.6.0.dist-info/METADATA
casbin_pymongo_adapter-1.6.0.dist-info/WHEEL
casbin_pymongo_adapter-1.6.0.dist-info/top_level.txt
casbin_pymongo_adapter-1.6.0.dist-info/RECORD
